adsbcot/__init__.py
adsbcot/classes.py
adsbcot/commands.py
adsbcot/constants.py
adsbcot/functions.py
adsbcot-9.0.1.dist-info/licenses/LICENSE
adsbcot-9.0.1.dist-info/METADATA
adsbcot-9.0.1.dist-info/WHEEL
adsbcot-9.0.1.dist-info/entry_points.txt
adsbcot-9.0.1.dist-info/top_level.txt
adsbcot-9.0.1.dist-info/RECORD
