Metadata-Version: 2.4
Name: adsbcot
Version: 9.0.1
Summary: Monitor and analyze aviation surveillance data with TAK.
Home-page: https://github.com/snstac/adsbcot
Maintainer: Greg Albrecht <oss@undef.net>
Maintainer-email: oss@undef.net
License: Apache 2.0
Project-URL: CI: GitHub Actions, https://github.com/snstac/adsbcot/actions
Project-URL: GitHub: issues, https://github.com/snstac/adsbcot/issues
Project-URL: GitHub: repo, https://github.com/snstac/adsbcot
Keywords: Cursor on Target,Cursor-on-Target,CoT,ATAK,TAK,WinTAK,TAK,TAK Server,ADS-B,ADSB,Aircraft
Classifier: License :: OSI Approved :: Apache Software License
Classifier: Intended Audience :: Developers
Classifier: Programming Language :: Python
Classifier: Programming Language :: Python :: 3
Classifier: Programming Language :: Python :: 3 :: Only
Classifier: Development Status :: 5 - Production/Stable
Classifier: Operating System :: POSIX
Classifier: Operating System :: MacOS :: MacOS X
Classifier: Operating System :: Microsoft :: Windows
Classifier: Operating System :: OS Independent
Requires-Python: <4,>=3.6
License-File: LICENSE
Requires-Dist: aircot>=1.2.0
Requires-Dist: pytak>=5.4.0
Requires-Dist: aiohttp<4.0.0
Requires-Dist: websockets<11.0.0
Provides-Extra: with-pymodes
Requires-Dist: pymodes>=2.8; extra == "with-pymodes"
Provides-Extra: with-takproto
Requires-Dist: takproto>=2.0.0; extra == "with-takproto"
Provides-Extra: with-asyncinotify
Requires-Dist: asyncinotify; extra == "with-asyncinotify"
Provides-Extra: test
Requires-Dist: pytest-asyncio; extra == "test"
Requires-Dist: pytest-cov; extra == "test"
Requires-Dist: pylint; extra == "test"
Requires-Dist: flake8; extra == "test"
Requires-Dist: black; extra == "test"
Dynamic: license-file
